HX711.cpython-39-arm-linux-gnueabihf.so
hx711_rpi_py-1.59.0.dist-info/LICENSE
hx711_rpi_py-1.59.0.dist-info/METADATA
hx711_rpi_py-1.59.0.dist-info/WHEEL
hx711_rpi_py-1.59.0.dist-info/top_level.txt
hx711_rpi_py-1.59.0.dist-info/RECORD
