Metadata-Version: 2.1
Name: hx711-rpi-py
Version: 1.59.0
Summary: Python bindings for Raspberry Pi HX711 C++ Library
Home-page: https://github.com/endail/hx711-rpi-py
Author: Daniel Robertson
Author-email: 52652357+endail@users.noreply.github.com
License: MIT
Keywords: hx711,raspberry-pi,sensor,weight,load-cell
Classifier: Development Status :: 5 - Production/Stable
Classifier: Intended Audience :: Developers
Classifier: License :: OSI Approved :: MIT License
Classifier: Programming Language :: Python :: 3
Classifier: Programming Language :: Python :: 3.6
Classifier: Programming Language :: Python :: 3.7
Classifier: Programming Language :: Python :: 3.8
Classifier: Programming Language :: Python :: 3.9
Classifier: Programming Language :: Python :: 3.10
Classifier: Programming Language :: Python :: 3 :: Only
Classifier: Topic :: Software Development
Classifier: Topic :: Home Automation
Classifier: Topic :: Scientific/Engineering
Classifier: Topic :: System :: Hardware :: Hardware Drivers
Classifier: Operating System :: POSIX :: Linux
Requires-Python: >=3.6, <4
License-File: LICENSE
